flitter_lang-1.0.0b28.dist-info/RECORD
flitter_lang-1.0.0b28.dist-info/WHEEL
flitter_lang-1.0.0b28.dist-info/entry_points.txt
flitter_lang-1.0.0b28.dist-info/top_level.txt
flitter_lang-1.0.0b28.dist-info/METADATA
flitter_lang-1.0.0b28.dist-info/licenses/LICENSE
flitter/plugins.py
flitter/streams.py
flitter/model.cpython-311-darwin.so
flitter/model.c
flitter/timer.pxd
flitter/clock.py
flitter/cache.py
flitter/__init__.py
flitter/model.pxd
flitter/ableton/events.py
flitter/ableton/constants.py
flitter/ableton/__init__.py
flitter/ableton/palette.py
flitter/ableton/push.py
flitter/render/osc.py
flitter/render/laser.cpython-311-darwin.so
flitter/render/laser.c
flitter/render/dmx.cpython-311-darwin.so
flitter/render/dmx.c
flitter/render/__init__.py
flitter/render/physics.c
flitter/render/physics.cpython-311-darwin.so
flitter/render/counter.c
flitter/render/counter.cpython-311-darwin.so
flitter/render/controller/midi.py
flitter/render/controller/__init__.py
flitter/render/controller/xtouch_mini.py
flitter/render/controller/push2.py
flitter/render/controller/driver.py
flitter/render/window/canvas3d.cpython-311-darwin.so
flitter/render/window/canvas.c
flitter/render/window/glconstants.py
flitter/render/window/models.c
flitter/render/window/__init__.py
flitter/render/window/record.py
flitter/render/window/canvas.cpython-311-darwin.so
flitter/render/window/target.py
flitter/render/window/models.cpython-311-darwin.so
flitter/render/window/models.pxd
flitter/render/window/video.py
flitter/render/window/image.py
flitter/render/window/canvas3d.c
flitter/render/window/shaders.py
flitter/render/window/glsl/edges.frag
flitter/render/window/glsl/noise.frag
flitter/render/window/glsl/lighting_functions.glsl
flitter/render/window/glsl/video.vert
flitter/render/window/glsl/noise_functions.glsl
flitter/render/window/glsl/default.vert
flitter/render/window/glsl/__init__.py
flitter/render/window/glsl/standard_lighting.vert
flitter/render/window/glsl/bloom.frag
flitter/render/window/glsl/blur.frag
flitter/render/window/glsl/video.frag
flitter/render/window/glsl/ease_functions.glsl
flitter/render/window/glsl/vignette.frag
flitter/render/window/glsl/color_functions.glsl
