Metadata-Version: 2.4
Name: flitter-lang
Version: 1.0.0b28
Summary: Flitter is a functional programming language and declarative system for describing 2D and 3D visuals
Author-email: Jonathan Hogg <me@jonathanhogg.com>
Maintainer-email: Jonathan Hogg <me@jonathanhogg.com>
License-Expression: BSD-2-Clause
Project-URL: Documentation, https://flitter.readthedocs.io/
Project-URL: Repository, https://github.com/jonathanhogg/flitter.git
Project-URL: Issues, https://github.com/jonathanhogg/flitter/issues
Keywords: language,opengl,live-coding,live-visuals
Classifier: Development Status :: 4 - Beta
Classifier: Intended Audience :: Developers
Classifier: Programming Language :: Python :: 3
Classifier: Programming Language :: Python :: 3.10
Classifier: Programming Language :: Python :: 3.11
Classifier: Programming Language :: Python :: 3.12
Classifier: Programming Language :: Python :: 3.13
Classifier: Environment :: Console
Classifier: Environment :: GPU
Classifier: Environment :: MacOS X
Classifier: Environment :: X11 Applications
Classifier: Topic :: Artistic Software
Classifier: Topic :: Multimedia :: Graphics
Classifier: Topic :: Multimedia :: Graphics :: 3D Rendering
Requires-Python: >=3.10
License-File: LICENSE
Requires-Dist: av
Requires-Dist: glfw
Requires-Dist: lark
Requires-Dist: loguru
Requires-Dist: mako
Requires-Dist: manifold3d
Requires-Dist: moderngl
Requires-Dist: networkx
Requires-Dist: numpy
Requires-Dist: pillow>=10.1.0
Requires-Dist: pyserial
Requires-Dist: pyusb
Requires-Dist: regex
Requires-Dist: rtmidi2
Requires-Dist: scipy
Requires-Dist: skia-python>=138.0
Requires-Dist: trimesh
Provides-Extra: macos
Requires-Dist: pyobjc-core; extra == "macos"
Requires-Dist: pyobjc-framework-Cocoa; extra == "macos"
Dynamic: license-file
